{
  "name": "Mage",
  "type": "cclass",
  "img": "icons/weapons/wands/wand-gem-violet.webp",
  "effects": [],
  "folder": "twKHkLNCYFslTClk",
  "flags": {
    "core": {}
  },
  "system": {
    "description": "",
    "level": 1,
    "bonus": null,
    "top_cf": "0.01",
    "hp": 0,
    "features": {
      "sp": true,
      "atk": true,
      "def": false,
      "spd": false,
      "spdm": false,
      "spdr": false,
      "init": true,
      "back": false,
      "luck": false,
      "assn": false
    },
    "caps": {
      "fcast": false,
      "hprof": false
    },
    "ptable": {
      "1": {
        "hp": {
          "value": null,
          "die": "1d4",
          "reroll": false
        },
        "atk": {
          "value": 0
        },
        "init": {
          "value": 2
        },
        "sp": {
          "value": 140
        },
        "back": {
          "value": ""
        },
        "luck": {
          "value": null
        }
      },
      "2": {
        "hp": {
          "die": "1d4",
          "reroll": true
        },
        "atk": {
          "value": 0
        },
        "init": {
          "value": 2
        },
        "sp": {
          "value": 190
        },
        "back": {
          "value": ""
        },
        "luck": {
          "value": null
        }
      },
      "3": {
        "hp": {
          "die": "1d4",
          "reroll": false
        },
        "atk": {
          "value": 0
        },
        "init": {
          "value": 2
        },
        "sp": {
          "value": 260
        },
        "back": {
          "value": ""
        },
        "luck": {
          "value": null
        }
      },
      "4": {
        "hp": {
          "die": "1d4",
          "reroll": true
        },
        "atk": {
          "value": 0
        },
        "init": {
          "value": 2
        },
        "sp": {
          "value": 340
        },
        "back": {
          "value": ""
        },
        "luck": {
          "value": null
        }
      },
      "5": {
        "hp": {
          "die": "1d4",
          "reroll": false
        },
        "atk": {
          "value": 1
        },
        "init": {
          "value": 1
        },
        "sp": {
          "value": 430
        },
        "back": {
          "value": ""
        },
        "luck": {
          "value": null
        }
      },
      "6": {
        "hp": {
          "die": "1d4",
          "reroll": true
        },
        "atk": {
          "value": 1
        },
        "init": {
          "value": 1
        },
        "sp": {
          "value": 530
        },
        "back": {
          "value": ""
        },
        "luck": {
          "value": null
        }
      },
      "7": {
        "hp": {
          "die": "1d4",
          "reroll": false
        },
        "atk": {
          "value": 1
        },
        "init": {
          "value": 1
        },
        "sp": {
          "value": 640
        },
        "back": {
          "value": ""
        },
        "luck": {
          "value": null
        }
      },
      "8": {
        "hp": {
          "die": "1d4",
          "reroll": true
        },
        "atk": {
          "value": 1
        },
        "init": {
          "value": 1
        },
        "sp": {
          "value": 760
        },
        "back": {
          "value": ""
        },
        "luck": {
          "value": null
        }
      },
      "9": {
        "hp": {
          "die": "1d4",
          "reroll": false
        },
        "atk": {
          "value": 1
        },
        "init": {
          "value": 1
        },
        "sp": {
          "value": 890
        },
        "back": {
          "value": ""
        },
        "luck": {
          "value": null
        }
      },
      "10": {
        "hp": {
          "die": "1d4",
          "reroll": true
        },
        "atk": {
          "value": 1
        },
        "init": {
          "value": 1
        },
        "sp": {
          "value": 1030
        },
        "back": {
          "value": ""
        },
        "luck": {
          "value": null
        }
      },
      "11": {
        "hp": {
          "die": "1d4",
          "reroll": false
        },
        "atk": {
          "value": 2
        },
        "init": {
          "value": 0
        },
        "sp": {
          "value": 1180
        },
        "back": {
          "value": ""
        },
        "luck": {
          "value": null
        }
      },
      "12": {
        "hp": {
          "die": "1d4",
          "reroll": true
        },
        "atk": {
          "value": 2
        },
        "init": {
          "value": 0
        },
        "sp": {
          "value": 1340
        },
        "back": {
          "value": ""
        },
        "luck": {
          "value": null
        }
      },
      "13": {
        "hp": {
          "die": "1d4",
          "reroll": false
        },
        "atk": {
          "value": 2
        },
        "init": {
          "value": 0
        },
        "sp": {
          "value": 1510
        },
        "back": {
          "value": ""
        },
        "luck": {
          "value": null
        }
      },
      "14": {
        "hp": {
          "die": "1d4",
          "reroll": true
        },
        "atk": {
          "value": 2
        },
        "init": {
          "value": 0
        },
        "sp": {
          "value": 1690
        },
        "back": {
          "value": ""
        },
        "luck": {
          "value": null
        }
      },
      "15": {
        "hp": {
          "die": "1d4",
          "reroll": false
        },
        "atk": {
          "value": 2
        },
        "init": {
          "value": 0
        },
        "sp": {
          "value": 1880
        },
        "back": {
          "value": ""
        },
        "luck": {
          "value": null
        }
      },
      "16": {
        "hp": {
          "die": "1d4",
          "reroll": true
        },
        "atk": {
          "value": 2
        },
        "init": {
          "value": 0
        },
        "sp": {
          "value": 2080
        },
        "back": {
          "value": ""
        },
        "luck": {
          "value": null
        }
      },
      "17": {
        "hp": {
          "die": "1d4",
          "reroll": false
        },
        "atk": {
          "value": 3
        },
        "init": {
          "value": 0
        },
        "sp": {
          "value": 2290
        },
        "back": {
          "value": ""
        },
        "luck": {
          "value": null
        }
      },
      "18": {
        "hp": {
          "die": "1d4",
          "reroll": true
        },
        "atk": {
          "value": 3
        },
        "init": {
          "value": 0
        },
        "sp": {
          "value": 2510
        },
        "back": {
          "value": ""
        },
        "luck": {
          "value": null
        }
      },
      "19": {
        "hp": {
          "die": "1d4",
          "reroll": false
        },
        "atk": {
          "value": 3
        },
        "init": {
          "value": -1
        },
        "sp": {
          "value": 2740
        },
        "back": {
          "value": ""
        },
        "luck": {
          "value": null
        }
      },
      "20": {
        "hp": {
          "die": "1d4",
          "reroll": true
        },
        "atk": {
          "value": 3
        },
        "init": {
          "value": -1
        },
        "sp": {
          "value": 2980
        },
        "back": {
          "value": ""
        },
        "luck": {
          "value": null
        }
      }
    }
  },
  "_stats": {
    "systemId": "hackmaster5e",
    "systemVersion": "0",
    "coreVersion": "11.305",
    "createdTime": 1688862766873,
    "modifiedTime": 1688862766905,
    "lastModifiedBy": "6PGvwKmaOsPz0R2y"
  },
  "_id": "GERp0iqbrU3WdSW0",
  "sort": 100000,
  "ownership": {
    "default": 0,
    "6PGvwKmaOsPz0R2y": 3
  },
  "_key": "!items!GERp0iqbrU3WdSW0"
}
